doona_taos_edge_model/__init__.py
doona_taos_edge_model/deploy_model.py
doona_taos_edge_model/deploy_pipeline.py
doona_taos_edge_model/model_predictor.py
doona_taos_edge_model/schema/ml.py
doona_taos_edge_model/schema/pipeline.py
doona_taos_edge_model/schema/stats.py
doona_taos_edge_model-0.2.0.dist-info/METADATA
doona_taos_edge_model-0.2.0.dist-info/WHEEL
doona_taos_edge_model-0.2.0.dist-info/top_level.txt
doona_taos_edge_model-0.2.0.dist-info/RECORD
